proxytypes3
