Metadata-Version: 2.1
Name: proxytypes3
Version: 1.0.1
Summary: General purpose proxy and wrapper types.
Home-page: https://github.com/chrisspen/ProxyTypes3
Author: Chris Spencer
Author-email: chrisspen@gmail.com
License: MIT
Platform: UNKNOWN
Classifier: Development Status :: 6 - Mature
Classifier: Intended Audience :: Developers
Classifier: License :: OSI Approved :: MIT License
Classifier: Operating System :: OS Independent
Classifier: Programming Language :: Python
Classifier: Programming Language :: Python :: 2.7
Classifier: Programming Language :: Python :: 3.4
Classifier: Programming Language :: Python :: 3.5
Classifier: Programming Language :: Python :: 3.6
